README.md
setup.py
bin/sapi
sapi.egg-info/PKG-INFO
sapi.egg-info/SOURCES.txt
sapi.egg-info/dependency_links.txt
sapi.egg-info/requires.txt
sapi.egg-info/top_level.txt
sapi_client/__init__.py
sapi_client/api_client.py
sapi_client/configuration.py
sapi_client/rest.py
sapi_client/apis/__init__.py
sapi_client/apis/introspect_api.py
sapi_client/apis/sapi_api.py
sapi_client/apis/storage_api.py
sapi_client/models/__init__.py
sapi_client/models/export_policy.py
sapi_client/models/lock.py
sapi_client/models/optional_from_snapshot.py
sapi_client/models/policy_rule.py
sapi_client/models/snapshot.py
sapi_client/models/snapshot_put.py
sapi_client/models/volume_create.py
sapi_client/models/volume_read.py
sapi_client/models/volume_write.py
test/__init__.py
test/test__api.py
test/test_export_policy.py
test/test_introspect_api.py
test/test_lock.py
test/test_optional_from_snapshot.py
test/test_policy_rule.py
test/test_sapi_api.py
test/test_snapshot.py
test/test_snapshot_put.py
test/test_storage_api.py
test/test_volume_create.py
test/test_volume_read.py
test/test_volume_write.py
test/local/__init__.py
test/local/test__api.py
test/local/test_export_policy.py
test/local/test_lock.py
test/local/test_optional_from_snapshot.py
test/local/test_policy_rule.py
test/local/test_snapshot.py
test/local/test_snapshot_put.py
test/local/test_storage_api.py
test/local/test_volume_create.py
test/local/test_volume_read.py
test/local/test_volume_write.py